{"abomasnow":["soundproof","snow-warning"],"abomasnow-mega":["snow-warning"],"abra":["synchronize","inner-focus","magic-guard"],"absol":["pressure","super-luck","justified"],"absol-mega":["magic-bounce"],"accelgor":["sticky-hold","unburden","hydration"],"aegislash-blade":["stance-change"],"aegislash-shield":["stance-change"],"aerodactyl":["pressure","rock-head","unnerve"],"aerodactyl-mega":["tough-claws"],"aggron":["sturdy","rock-head","heavy-metal"],"aggron-mega":["filter"],"aipom":["run-away","pickup","skill-link"],"alakazam":["synchronize","inner-focus","magic-guard"],"alakazam-mega":["trace"],"alcremie":["aroma-veil","sweet-veil"],"alcremie-gmax":["aroma-veil","sweet-veil"],"alomomola":["hydration","healer","regenerator"],"altaria":["cloud-nine","natural-cure"],"altaria-mega":["pixilate"],"amaura":["snow-warning","refrigerate"],"ambipom":["pickup","skill-link","technician"],"amoonguss":["effect-spore","regenerator"],"ampharos":["static","plus"],"ampharos-mega":["mold-breaker"],"annihilape":["inner-focus","vital-spirit","defiant"],"anorith":["battle-armor","swift-swim"],"appletun":["thick-fat","gluttony","ripen"],"appletun-gmax":["thick-fat","gluttony","ripen"],"applin":["gluttony","bulletproof","ripen"],"araquanid":["water-absorb","water-bubble"],"araquanid-totem":["water-absorb","water-bubble"],"arbok":["intimidate","shed-skin","unnerve"],"arboliva":["harvest","seed-sower"],"arcanine":["flash-fire","intimidate","justified"],"arcanine-hisui":["flash-fire","intimidate","rock-head"],"arceus":["multitype"],"archaludon":["sturdy","stamina","stalwart"],"archen":["defeatist"],"archeops":["defeatist"],"arctibax":["ice-body","thermal-exchange"],"arctovish":["water-absorb","ice-body","slush-rush"],"arctozolt":["static","volt-absorb","slush-rush"],"ariados":["insomnia","swarm","sniper"],"armaldo":["battle-armor","swift-swim"],"armarouge":["flash-fire","weak-armor"],"aromatisse":["healer","aroma-veil"],"aron":["sturdy","rock-head","heavy-metal"],"arrokuda":["swift-swim","propeller-tail"],"articuno":["pressure","snow-cloak"],"articuno-galar":["competitive"],"audino":["klutz","healer","regenerator"],"audino-mega":["healer"],"aurorus":["snow-warning","refrigerate"],"avalugg":["sturdy","own-tempo","ice-body"],"avalugg-hisui":["sturdy","ice-body","strong-jaw"],"axew":["rivalry","mold-breaker","unnerve"],"azelf":["levitate"],"azumarill":["huge-power","thick-fat","sap-sipper"],"azurill":["huge-power","thick-fat","sap-sipper"],"bagon":["rock-head","sheer-force"],"baltoy":["levitate"],"banette":["insomnia","frisk","cursed-body"],"banette-mega":["prankster"],"barbaracle":["sniper","pickpocket","tough-claws"],"barboach":["oblivious","hydration","anticipation"],"barraskewda":["swift-swim","propeller-tail"],"basculegion-female":["swift-swim","adaptability","mold-breaker"],"basculegion-male":["swift-swim","adaptability","mold-breaker"],"basculin-blue-striped":["rock-head","adaptability","mold-breaker"],"basculin-red-striped":["adaptability","mold-breaker","reckless"],"basculin-white-striped":["adaptability","mold-breaker","rattled"],"bastiodon":["sturdy","soundproof"],"baxcalibur":["ice-body","thermal-exchange"],"bayleef":["overgrow","leaf-guard"],"beartic":["swift-swim","snow-cloak","slush-rush"],"beautifly":["swarm","rivalry"],"beedrill":["swarm","sniper"],"beedrill-mega":["adaptability"],"beheeyem":["synchronize","telepathy","analytic"],"beldum":["clear-body","light-metal"],"bellibolt":["damp","static","electromorphosis"],"bellossom":["chlorophyll","healer"],"bellsprout":["chlorophyll","gluttony"],"bergmite":["sturdy","own-tempo","ice-body"],"bewear":["klutz","unnerve","fluffy"],"bibarel":["simple","unaware","moody"],"bidoof":["simple","unaware","moody"],"binacle":["sniper","pickpocket","tough-claws"],"bisharp":["inner-focus","pressure","defiant"],"blacephalon":["beast-boost"],"blastoise":["rain-dish","torrent"],"blastoise-gmax":["rain-dish","torrent"],"blastoise-mega":["mega-launcher"],"blaziken":["speed-boost","blaze"],"blaziken-mega":["speed-boost"],"blipbug":["compound-eyes","swarm","telepathy"],"blissey":["natural-cure","serene-grace","healer"],"blitzle":["lightning-rod","motor-drive","sap-sipper"],"boldore":["sturdy","weak-armor","sand-force"],"boltund":["competitive","strong-jaw"],"bombirdier":["keen-eye","big-pecks","rocky-payload"],"bonsly":["sturdy","rock-head","rattled"],"bouffalant":["soundproof","reckless","sap-sipper"],"bounsweet":["oblivious","leaf-guard","sweet-veil"],"braixen":["blaze","magician"],"brambleghast":["infiltrator","wind-rider"],"bramblin":["infiltrator","wind-rider"],"braviary":["keen-eye","sheer-force","defiant"],"braviary-hisui":["keen-eye","tinted-lens","sheer-force"],"breloom":["effect-spore","poison-heal","technician"],"brionne":["torrent","liquid-voice"],"bronzong":["levitate","heatproof","heavy-metal"],"bronzor":["levitate","heatproof","heavy-metal"],"brute-bonnet":["protosynthesis","protosynthesis"],"bruxish":["wonder-skin","strong-jaw","dazzling"],"budew":["natural-cure","poison-point","leaf-guard"],"buizel":["swift-swim","water-veil"],"bulbasaur":["chlorophyll","overgrow"],"buneary":["limber","run-away","klutz"],"bunnelby":["huge-power","pickup","cheek-pouch"],"burmy":["shed-skin","overcoat"],"butterfree":["compound-eyes","tinted-lens"],"butterfree-gmax":["compound-eyes","tinted-lens"],"buzzwole":["beast-boost"],"cacnea":["sand-veil","water-absorb"],"cacturne":["sand-veil","water-absorb"],"calyrex":["unnerve"],"calyrex-ice":["as-one-glastrier"],"calyrex-shadow":["as-one-spectrier"],"camerupt":["magma-armor","anger-point","solid-rock"],"camerupt-mega":["sheer-force"],"capsakid":["insomnia","chlorophyll","klutz"],"carbink":["sturdy","clear-body"],"carkol":["flash-fire","flame-body","steam-engine"],"carnivine":["levitate"],"carracosta":["sturdy","swift-swim","solid-rock"],"carvanha":["speed-boost","rough-skin"],"cascoon":["shed-skin"],"castform":["forecast"],"castform-rainy":["forecast"],"castform-snowy":["forecast"],"castform-sunny":["forecast"],"caterpie":["shield-dust","run-away"],"celebi":["natural-cure"],"celesteela":["beast-boost"],"centiskorch":["flash-fire","flame-body","white-smoke"],"centiskorch-gmax":["flash-fire","flame-body","white-smoke"],"ceruledge":["flash-fire","weak-armor"],"cetitan":["thick-fat","sheer-force","slush-rush"],"cetoddle":["thick-fat","snow-cloak","sheer-force"],"chandelure":["flash-fire","flame-body","infiltrator"],"chansey":["natural-cure","serene-grace","healer"],"charcadet":["flash-fire","flame-body"],"charizard":["blaze","solar-power"],"charizard-gmax":["blaze","solar-power"],"charizard-mega-x":["tough-claws"],"charizard-mega-y":["drought"],"charjabug":["battery"],"charmander":["blaze","solar-power"],"charmeleon":["blaze","solar-power"],"chatot":["keen-eye","tangled-feet","big-pecks"],"cherrim":["flower-gift"],"cherubi":["chlorophyll"],"chesnaught":["overgrow","bulletproof"],"chespin":["overgrow","bulletproof"],"chewtle":["swift-swim","shell-armor","strong-jaw"],"chi-yu":["beads-of-ruin","beads-of-ruin"],"chien-pao":["sword-of-ruin","sword-of-ruin"],"chikorita":["overgrow","leaf-guard"],"chimchar":["blaze","iron-fist"],"chimecho":["levitate"],"chinchou":["volt-absorb","water-absorb","illuminate"],"chingling":["levitate"],"cinccino":["cute-charm","skill-link","technician"],"cinderace":["blaze","libero"],"cinderace-gmax":["blaze","libero"],"clamperl":["shell-armor","rattled"],"clauncher":["mega-launcher"],"clawitzer":["mega-launcher"],"claydol":["levitate"],"clefable":["cute-charm","magic-guard","unaware"],"clefairy":["cute-charm","magic-guard","friend-guard"],"cleffa":["cute-charm","magic-guard","friend-guard"],"clobbopus":["limber","technician"],"clodsire":["water-absorb","poison-point","unaware"],"cloyster":["shell-armor","skill-link","overcoat"],"coalossal":["flash-fire","flame-body","steam-engine"],"coalossal-gmax":["flash-fire","flame-body","steam-engine"],"cobalion":["justified"],"cofagrigus":["mummy"],"combee":["hustle","honey-gather"],"combusken":["speed-boost","blaze"],"comfey":["natural-cure","flower-veil","triage"],"conkeldurr":["guts","iron-fist","sheer-force"],"copperajah":["sheer-force","heavy-metal"],"copperajah-gmax":["sheer-force","heavy-metal"],"corphish":["hyper-cutter","shell-armor","adaptability"],"corsola":["natural-cure","hustle","regenerator"],"corsola-galar":["cursed-body","weak-armor"],"corviknight":["pressure","unnerve","mirror-armor"],"corviknight-gmax":["pressure","unnerve","mirror-armor"],"corvisquire":["keen-eye","unnerve","big-pecks"],"cosmoem":["sturdy"],"cosmog":["unaware"],"cottonee":["chlorophyll","infiltrator","prankster"],"crabominable":["hyper-cutter","anger-point","iron-fist"],"crabrawler":["hyper-cutter","anger-point","iron-fist"],"cradily":["suction-cups","storm-drain"],"cramorant":["gulp-missile"],"cramorant-gorging":["gulp-missile"],"cramorant-gulping":["gulp-missile"],"cranidos":["mold-breaker","sheer-force"],"crawdaunt":["hyper-cutter","shell-armor","adaptability"],"cresselia":["levitate"],"croagunk":["dry-skin","anticipation","poison-touch"],"crobat":["inner-focus","infiltrator"],"crocalor":["blaze","unaware"],"croconaw":["torrent","sheer-force"],"crustle":["sturdy","shell-armor","weak-armor"],"cryogonal":["levitate"],"cubchoo":["snow-cloak","rattled","slush-rush"],"cubone":["battle-armor","lightning-rod","rock-head"],"cufant":["sheer-force","heavy-metal"],"cursola":["weak-armor","perish-body"],"cutiefly":["shield-dust","honey-gather","sweet-veil"],"cyclizar":["shed-skin","regenerator"],"cyndaquil":["flash-fire","blaze"],"dachsbun":["aroma-veil","well-baked-body"],"darkrai":["bad-dreams"],"darmanitan-galar-standard":["zen-mode","gorilla-tactics"],"darmanitan-galar-zen":["zen-mode","gorilla-tactics"],"darmanitan-standard":["sheer-force","zen-mode"],"darmanitan-zen":["sheer-force","zen-mode"],"dartrix":["overgrow","long-reach"],"darumaka":["inner-focus","hustle"],"darumaka-galar":["inner-focus","hustle"],"decidueye":["overgrow","long-reach"],"decidueye-hisui":["overgrow","scrappy"],"dedenne":["pickup","plus","cheek-pouch"],"deerling":["serene-grace","chlorophyll","sap-sipper"],"deino":["hustle"],"delcatty":["cute-charm","normalize","wonder-skin"],"delibird":["insomnia","hustle","vital-spirit"],"delphox":["blaze","magician"],"deoxys-attack":["pressure"],"deoxys-defense":["pressure"],"deoxys-normal":["pressure"],"deoxys-speed":["pressure"],"dewgong":["thick-fat","hydration","ice-body"],"dewott":["torrent","shell-armor"],"dewpider":["water-absorb","water-bubble"],"dhelmise":["steelworker"],"dialga":["pressure","telepathy"],"dialga-origin":["pressure","telepathy"],"diancie":["clear-body"],"diancie-mega":["magic-bounce"],"diggersby":["huge-power","pickup","cheek-pouch"],"diglett":["sand-veil","arena-trap","sand-force"],"diglett-alola":["sand-veil","sand-force","tangling-hair"],"dipplin":["sticky-hold","gluttony","supersweet-syrup"],"ditto":["limber","imposter"],"dodrio":["early-bird","run-away","tangled-feet"],"doduo":["early-bird","run-away","tangled-feet"],"dolliv":["early-bird","harvest"],"dondozo":["oblivious","water-veil","unaware"],"donphan":["sturdy","sand-veil"],"dottler":["compound-eyes","swarm","telepathy"],"doublade":["no-guard"],"dracovish":["water-absorb","sand-rush","strong-jaw"],"dracozolt":["volt-absorb","hustle","sand-rush"],"dragalge":["poison-point","adaptability","poison-touch"],"dragapult":["clear-body","cursed-body","infiltrator"],"dragonair":["shed-skin","marvel-scale"],"dragonite":["inner-focus","multiscale"],"drakloak":["clear-body","cursed-body","infiltrator"],"drampa":["cloud-nine","sap-sipper","berserk"],"drapion":["battle-armor","keen-eye","sniper"],"dratini":["shed-skin","marvel-scale"],"drednaw":["swift-swim","shell-armor","strong-jaw"],"drednaw-gmax":["swift-swim","shell-armor","strong-jaw"],"dreepy":["clear-body","cursed-body","infiltrator"],"drifblim":["unburden","aftermath","flare-boost"],"drifloon":["unburden","aftermath","flare-boost"],"drilbur":["mold-breaker","sand-rush","sand-force"],"drizzile":["torrent","sniper"],"drowzee":["insomnia","inner-focus","forewarn"],"druddigon":["rough-skin","mold-breaker","sheer-force"],"dubwool":["steadfast","bulletproof","fluffy"],"ducklett":["keen-eye","hydration","big-pecks"],"dudunsparce-three-segment":["serene-grace","run-away","rattled"],"dudunsparce-two-segment":["serene-grace","run-away","rattled"],"dugtrio":["sand-veil","arena-trap","sand-force"],"dugtrio-alola":["sand-veil","sand-force","tangling-hair"],"dunsparce":["serene-grace","run-away","rattled"],"duosion":["magic-guard","overcoat","regenerator"],"duraludon":["heavy-metal","light-metal","stalwart"],"duraludon-gmax":["heavy-metal","light-metal","stalwart"],"durant":["truant","hustle","swarm"],"dusclops":["pressure","frisk"],"dusknoir":["pressure","frisk"],"duskull":["levitate","frisk"],"dustox":["compound-eyes","shield-dust"],"dwebble":["sturdy","shell-armor","weak-armor"],"eelektrik":["levitate"],"eelektross":["levitate"],"eevee":["run-away","adaptability","anticipation"],"eevee-gmax":["run-away","adaptability","anticipation"],"eevee-starter":["run-away","adaptability","anticipation"],"eiscue-ice":["ice-face"],"eiscue-noice":["ice-face"],"ekans":["intimidate","shed-skin","unnerve"],"eldegoss":["effect-spore","regenerator","cotton-down"],"electabuzz":["static","vital-spirit"],"electivire":["vital-spirit","motor-drive"],"electrike":["static","lightning-rod","minus"],"electrode":["static","soundproof","aftermath"],"electrode-hisui":["static","soundproof","aftermath"],"elekid":["static","vital-spirit"],"elgyem":["synchronize","telepathy","analytic"],"emboar":["blaze","reckless"],"emolga":["static","motor-drive"],"empoleon":["torrent","competitive"],"enamorus-incarnate":["cute-charm","contrary"],"enamorus-therian":["overcoat"],"entei":["inner-focus","pressure"],"escavalier":["swarm","shell-armor","overcoat"],"espathra":["speed-boost","frisk","opportunist"],"espeon":["synchronize","magic-bounce"],"espurr":["own-tempo","keen-eye","infiltrator"],"eternatus":["pressure"],"eternatus-eternamax":["pressure"],"excadrill":["mold-breaker","sand-rush","sand-force"],"exeggcute":["chlorophyll","harvest"],"exeggutor":["chlorophyll","harvest"],"exeggutor-alola":["frisk","harvest"],"exploud":["soundproof","scrappy"],"falinks":["battle-armor","defiant"],"farfetchd":["inner-focus","keen-eye","defiant"],"farfetchd-galar":["steadfast","scrappy"],"farigiraf":["sap-sipper","cud-chew","armor-tail"],"fearow":["keen-eye","sniper"],"feebas":["oblivious","swift-swim","adaptability"],"fennekin":["blaze","magician"],"feraligatr":["torrent","sheer-force"],"ferroseed":["iron-barbs"],"ferrothorn":["anticipation","iron-barbs"],"fezandipiti":["technician","toxic-chain"],"fidough":["own-tempo","klutz"],"finizen":["water-veil","water-veil"],"finneon":["swift-swim","water-veil","storm-drain"],"flaaffy":["static","plus"],"flabebe":["flower-veil","symbiosis"],"flamigo":["tangled-feet","scrappy","costar"],"flapple":["hustle","gluttony","ripen"],"flapple-gmax":["hustle","gluttony","ripen"],"flareon":["flash-fire","guts"],"fletchinder":["flame-body","gale-wings"],"fletchling":["big-pecks","gale-wings"],"flittle":["speed-boost","anticipation","frisk"],"floatzel":["swift-swim","water-veil"],"floette":["flower-veil","symbiosis"],"floette-eternal":["flower-veil","symbiosis"],"floragato":["overgrow","protean"],"florges":["flower-veil","symbiosis"],"flutter-mane":["protosynthesis","protosynthesis"],"flygon":["levitate"],"fomantis":["leaf-guard","contrary"],"foongus":["effect-spore","regenerator"],"forretress":["sturdy","overcoat"],"fraxure":["rivalry","mold-breaker","unnerve"],"frigibax":["ice-body","thermal-exchange"],"frillish":["damp","water-absorb","cursed-body"],"froakie":["torrent","protean"],"frogadier":["torrent","protean"],"froslass":["snow-cloak","cursed-body"],"frosmoth":["shield-dust","ice-scales"],"fuecoco":["blaze","unaware"],"furfrou":["fur-coat"],"furret":["run-away","keen-eye","frisk"],"gabite":["sand-veil","rough-skin"],"gallade":["steadfast","justified","sharpness"],"gallade-mega":["inner-focus"],"galvantula":["compound-eyes","swarm","unnerve"],"garbodor":["stench","aftermath","weak-armor"],"garbodor-gmax":["stench","aftermath","weak-armor"],"garchomp":["sand-veil","rough-skin"],"garchomp-mega":["sand-force"],"gardevoir":["synchronize","trace","telepathy"],"gardevoir-mega":["pixilate"],"garganacl":["sturdy","clear-body","purifying-salt"],"gastly":["levitate"],"gastrodon":["sticky-hold","storm-drain","sand-force"],"genesect":["download"],"gengar":["cursed-body"],"gengar-gmax":["cursed-body"],"gengar-mega":["shadow-tag"],"geodude":["sturdy","sand-veil","rock-head"],"geodude-alola":["sturdy","magnet-pull","galvanize"],"gholdengo":["good-as-gold","good-as-gold"],"gible":["sand-veil","rough-skin"],"gigalith":["sturdy","sand-stream","sand-force"],"gimmighoul":["rattled","rattled"],"gimmighoul-roaming":["run-away","run-away"],"girafarig":["inner-focus","early-bird","sap-sipper"],"giratina-altered":["pressure","telepathy"],"giratina-origin":["levitate"],"glaceon":["snow-cloak","ice-body"],"glalie":["inner-focus","ice-body","moody"],"glalie-mega":["refrigerate"],"glameow":["limber","own-tempo","keen-eye"],"glastrier":["chilling-neigh"],"gligar":["sand-veil","immunity","hyper-cutter"],"glimmet":["corrosion","toxic-debris"],"glimmora":["corrosion","toxic-debris"],"gliscor":["sand-veil","hyper-cutter","poison-heal"],"gloom":["stench","chlorophyll"],"gogoat":["sap-sipper","grass-pelt"],"golbat":["inner-focus","infiltrator"],"goldeen":["lightning-rod","swift-swim","water-veil"],"golduck":["damp","cloud-nine","swift-swim"],"golem":["sturdy","sand-veil","rock-head"],"golem-alola":["sturdy","magnet-pull","galvanize"],"golett":["iron-fist","no-guard","klutz"],"golisopod":["emergency-exit"],"golurk":["iron-fist","no-guard","klutz"],"goodra":["hydration","sap-sipper","gooey"],"goodra-hisui":["shell-armor","sap-sipper","gooey"],"goomy":["hydration","sap-sipper","gooey"],"gorebyss":["swift-swim","hydration"],"gossifleur":["effect-spore","regenerator","cotton-down"],"gothita":["shadow-tag","frisk","competitive"],"gothitelle":["shadow-tag","frisk","competitive"],"gothorita":["shadow-tag","frisk","competitive"],"gouging-fire":["protosynthesis"],"gourgeist-average":["insomnia","pickup","frisk"],"gourgeist-large":["insomnia","pickup","frisk"],"gourgeist-small":["insomnia","pickup","frisk"],"gourgeist-super":["insomnia","pickup","frisk"],"grafaiai":["unburden","poison-touch","prankster"],"granbull":["intimidate","quick-feet","rattled"],"grapploct":["limber","technician"],"graveler":["sturdy","sand-veil","rock-head"],"graveler-alola":["sturdy","magnet-pull","galvanize"],"great-tusk":["protosynthesis","protosynthesis"],"greavard":["pickup","fluffy"],"greedent":["gluttony","cheek-pouch"],"greninja":["torrent","protean"],"greninja-ash":["battle-bond"],"greninja-battle-bond":["battle-bond"],"grimer":["stench","sticky-hold","poison-touch"],"grimer-alola":["gluttony","poison-touch","power-of-alchemy"],"grimmsnarl":["frisk","pickpocket","prankster"],"grimmsnarl-gmax":["frisk","pickpocket","prankster"],"grookey":["overgrow","grassy-surge"],"grotle":["overgrow","shell-armor"],"groudon":["drought"],"groudon-primal":["desolate-land"],"grovyle":["overgrow","unburden"],"growlithe":["flash-fire","intimidate","justified"],"growlithe-hisui":["flash-fire","intimidate","rock-head"],"grubbin":["swarm"],"grumpig":["own-tempo","thick-fat","gluttony"],"gulpin":["sticky-hold","liquid-ooze","gluttony"],"gumshoos":["adaptability","strong-jaw","stakeout"],"gumshoos-totem":["adaptability","strong-jaw","stakeout"],"gurdurr":["guts","iron-fist","sheer-force"],"guzzlord":["beast-boost"],"gyarados":["intimidate","moxie"],"gyarados-mega":["mold-breaker"],"hakamo-o":["soundproof","overcoat","bulletproof"],"happiny":["natural-cure","serene-grace","friend-guard"],"hariyama":["thick-fat","guts","sheer-force"],"hatenna":["anticipation","healer","magic-bounce"],"hatterene":["anticipation","healer","magic-bounce"],"hatterene-gmax":["anticipation","healer","magic-bounce"],"hattrem":["anticipation","healer","magic-bounce"],"haunter":["levitate"],"hawlucha":["limber","unburden","mold-breaker"],"haxorus":["rivalry","mold-breaker","unnerve"],"heatmor":["flash-fire","white-smoke","gluttony"],"heatran":["flash-fire","flame-body"],"heliolisk":["sand-veil","dry-skin","solar-power"],"helioptile":["sand-veil","dry-skin","solar-power"],"heracross":["guts","swarm","moxie"],"heracross-mega":["skill-link"],"herdier":["intimidate","scrappy","sand-rush"],"hippopotas":["sand-stream","sand-force"],"hippowdon":["sand-stream","sand-force"],"hitmonchan":["inner-focus","keen-eye","iron-fist"],"hitmonlee":["limber","unburden","reckless"],"hitmontop":["intimidate","steadfast","technician"],"ho-oh":["pressure","regenerator"],"honchkrow":["insomnia","super-luck","moxie"],"honedge":["no-guard"],"hoopa":["magician"],"hoopa-unbound":["magician"],"hoothoot":["insomnia","keen-eye","tinted-lens"],"hoppip":["chlorophyll","leaf-guard","infiltrator"],"horsea":["damp","swift-swim","sniper"],"houndoom":["flash-fire","early-bird","unnerve"],"houndoom-mega":["solar-power"],"houndour":["flash-fire","early-bird","unnerve"],"houndstone":["sand-rush","fluffy"],"huntail":["swift-swim","water-veil"],"hydrapple":["sticky-hold","regenerator","supersweet-syrup"],"hydreigon":["levitate"],"hypno":["insomnia","inner-focus","forewarn"],"igglybuff":["cute-charm","friend-guard","competitive"],"illumise":["oblivious","tinted-lens","prankster"],"impidimp":["frisk","pickpocket","prankster"],"incineroar":["intimidate","blaze"],"indeedee-female":["own-tempo","synchronize","psychic-surge"],"indeedee-male":["synchronize","inner-focus","psychic-surge"],"infernape":["blaze","iron-fist"],"inkay":["suction-cups","contrary","infiltrator"],"inteleon":["torrent","sniper"],"inteleon-gmax":["torrent","sniper"],"iron-boulder":["quark-drive"],"iron-bundle":["quark-drive","quark-drive"],"iron-crown":["quark-drive"],"iron-hands":["quark-drive","quark-drive"],"iron-jugulis":["quark-drive","quark-drive"],"iron-leaves":["quark-drive","quark-drive"],"iron-moth":["quark-drive","quark-drive"],"iron-thorns":["quark-drive","quark-drive"],"iron-treads":["quark-drive","quark-drive"],"iron-valiant":["quark-drive","quark-drive"],"ivysaur":["chlorophyll","overgrow"],"jangmo-o":["soundproof","overcoat","bulletproof"],"jellicent":["damp","water-absorb","cursed-body"],"jigglypuff":["cute-charm","friend-guard","competitive"],"jirachi":["serene-grace"],"jolteon":["volt-absorb","quick-feet"],"joltik":["compound-eyes","swarm","unnerve"],"jumpluff":["chlorophyll","leaf-guard","infiltrator"],"jynx":["oblivious","dry-skin","forewarn"],"kabuto":["battle-armor","swift-swim","weak-armor"],"kabutops":["battle-armor","swift-swim","weak-armor"],"kadabra":["synchronize","inner-focus","magic-guard"],"kakuna":["shed-skin"],"kangaskhan":["inner-focus","early-bird","scrappy"],"kangaskhan-mega":["parental-bond"],"karrablast":["shed-skin","swarm","no-guard"],"kartana":["beast-boost"],"kecleon":["color-change","protean"],"keldeo-ordinary":["justified"],"keldeo-resolute":["justified"],"kilowattrel":["volt-absorb","competitive","wind-power"],"kingambit":["pressure","defiant","supreme-overlord"],"kingdra":["damp","swift-swim","sniper"],"kingler":["hyper-cutter","shell-armor","sheer-force"],"kingler-gmax":["hyper-cutter","shell-armor","sheer-force"],"kirlia":["synchronize","trace","telepathy"],"klang":["clear-body","plus","minus"],"klawf":["shell-armor","regenerator","anger-shell"],"kleavor":["swarm","sheer-force","sharpness"],"klefki":["prankster","magician"],"klink":["clear-body","plus","minus"],"klinklang":["clear-body","plus","minus"],"koffing":["stench","levitate","neutralizing-gas"],"komala":["comatose"],"kommo-o":["soundproof","overcoat","bulletproof"],"kommo-o-totem":["soundproof","overcoat","bulletproof"],"koraidon":["orichalcum-pulse","orichalcum-pulse"],"koraidon-gliding-build":["orichalcum-pulse","orichalcum-pulse"],"koraidon-limited-build":["orichalcum-pulse","orichalcum-pulse"],"koraidon-sprinting-build":["orichalcum-pulse","orichalcum-pulse"],"koraidon-swimming-build":["orichalcum-pulse","orichalcum-pulse"],"krabby":["hyper-cutter","shell-armor","sheer-force"],"kricketot":["run-away","shed-skin"],"kricketune":["swarm","technician"],"krokorok":["intimidate","anger-point","moxie"],"krookodile":["intimidate","anger-point","moxie"],"kubfu":["inner-focus"],"kyogre":["drizzle"],"kyogre-primal":["primordial-sea"],"kyurem":["pressure"],"kyurem-black":["teravolt"],"kyurem-white":["turboblaze"],"lairon":["sturdy","rock-head","heavy-metal"],"lampent":["flash-fire","flame-body","infiltrator"],"landorus-incarnate":["sheer-force","sand-force"],"landorus-therian":["intimidate"],"lanturn":["volt-absorb","water-absorb","illuminate"],"lapras":["water-absorb","shell-armor","hydration"],"lapras-gmax":["water-absorb","shell-armor","hydration"],"larvesta":["flame-body","swarm"],"larvitar":["sand-veil","guts"],"latias":["levitate"],"latias-mega":["levitate"],"latios":["levitate"],"latios-mega":["levitate"],"leafeon":["chlorophyll","leaf-guard"],"leavanny":["chlorophyll","swarm","overcoat"],"lechonk":["thick-fat","gluttony","aroma-veil"],"ledian":["early-bird","swarm","iron-fist"],"ledyba":["early-bird","swarm","rattled"],"lickilicky":["oblivious","cloud-nine","own-tempo"],"lickitung":["oblivious","cloud-nine","own-tempo"],"liepard":["limber","unburden","prankster"],"lileep":["suction-cups","storm-drain"],"lilligant":["own-tempo","chlorophyll","leaf-guard"],"lilligant-hisui":["chlorophyll","hustle","leaf-guard"],"lillipup":["run-away","pickup","vital-spirit"],"linoone":["pickup","gluttony","quick-feet"],"linoone-galar":["pickup","gluttony","quick-feet"],"litleo":["rivalry","unnerve","moxie"],"litten":["intimidate","blaze"],"litwick":["flash-fire","flame-body","infiltrator"],"lokix":["swarm","tinted-lens"],"lombre":["own-tempo","swift-swim","rain-dish"],"lopunny":["limber","cute-charm","klutz"],"lopunny-mega":["scrappy"],"lotad":["own-tempo","swift-swim","rain-dish"],"loudred":["soundproof","scrappy"],"lucario":["inner-focus","steadfast","justified"],"lucario-mega":["adaptability"],"ludicolo":["own-tempo","swift-swim","rain-dish"],"lugia":["pressure","multiscale"],"lumineon":["swift-swim","water-veil","storm-drain"],"lunala":["shadow-shield"],"lunatone":["levitate"],"lurantis":["leaf-guard","contrary"],"lurantis-totem":["leaf-guard","contrary"],"luvdisc":["swift-swim","hydration"],"luxio":["intimidate","guts","rivalry"],"luxray":["intimidate","guts","rivalry"],"lycanroc-dusk":["tough-claws"],"lycanroc-midday":["keen-eye","steadfast","sand-rush"],"lycanroc-midnight":["keen-eye","vital-spirit","no-guard"],"mabosstiff":["intimidate","stakeout","guard-dog"],"machamp":["guts","steadfast","no-guard"],"machamp-gmax":["guts","steadfast","no-guard"],"machoke":["guts","steadfast","no-guard"],"machop":["guts","steadfast","no-guard"],"magby":["flame-body","vital-spirit"],"magcargo":["magma-armor","flame-body","weak-armor"],"magearna":["soul-heart"],"magearna-original":["soul-heart"],"magikarp":["swift-swim","rattled"],"magmar":["flame-body","vital-spirit"],"magmortar":["flame-body","vital-spirit"],"magnemite":["sturdy","magnet-pull","analytic"],"magneton":["sturdy","magnet-pull","analytic"],"magnezone":["sturdy","magnet-pull","analytic"],"makuhita":["thick-fat","guts","sheer-force"],"malamar":["suction-cups","contrary","infiltrator"],"mamoswine":["oblivious","thick-fat","snow-cloak"],"manaphy":["hydration"],"mandibuzz":["weak-armor","overcoat","big-pecks"],"manectric":["static","lightning-rod","minus"],"manectric-mega":["intimidate"],"mankey":["vital-spirit","anger-point","defiant"],"mantine":["water-absorb","swift-swim","water-veil"],"mantyke":["water-absorb","swift-swim","water-veil"],"maractus":["water-absorb","chlorophyll","storm-drain"],"mareanie":["limber","regenerator","merciless"],"mareep":["static","plus"],"marill":["huge-power","thick-fat","sap-sipper"],"marowak":["battle-armor","lightning-rod","rock-head"],"marowak-alola":["lightning-rod","rock-head","cursed-body"],"marowak-totem":["lightning-rod","rock-head","cursed-body"],"marshadow":["technician"],"marshtomp":["damp","torrent"],"maschiff":["intimidate","run-away","stakeout"],"masquerain":["intimidate","unnerve"],"maushold-family-of-four":["technician","friend-guard","cheek-pouch"],"maushold-family-of-three":["technician","friend-guard","cheek-pouch"],"mawile":["intimidate","hyper-cutter","sheer-force"],"mawile-mega":["huge-power"],"medicham":["pure-power","telepathy"],"medicham-mega":["pure-power"],"meditite":["pure-power","telepathy"],"meganium":["overgrow","leaf-guard"],"melmetal":["iron-fist"],"melmetal-gmax":["iron-fist"],"meloetta-aria":["serene-grace"],"meloetta-pirouette":["serene-grace"],"meltan":["magnet-pull"],"meowscarada":["overgrow","protean"],"meowstic-female":["keen-eye","infiltrator","competitive"],"meowstic-male":["keen-eye","infiltrator","prankster"],"meowth":["pickup","technician","unnerve"],"meowth-alola":["pickup","technician","rattled"],"meowth-galar":["pickup","unnerve","tough-claws"],"meowth-gmax":["pickup","technician","unnerve"],"mesprit":["levitate"],"metagross":["clear-body","light-metal"],"metagross-mega":["tough-claws"],"metang":["clear-body","light-metal"],"metapod":["shed-skin"],"mew":["synchronize"],"mewtwo":["pressure","unnerve"],"mewtwo-mega-x":["steadfast"],"mewtwo-mega-y":["insomnia"],"mienfoo":["inner-focus","reckless","regenerator"],"mienshao":["inner-focus","reckless","regenerator"],"mightyena":["intimidate","quick-feet","moxie"],"milcery":["aroma-veil","sweet-veil"],"milotic":["cute-charm","marvel-scale","competitive"],"miltank":["thick-fat","scrappy","sap-sipper"],"mime-jr":["soundproof","technician","filter"],"mimikyu-busted":["disguise"],"mimikyu-disguised":["disguise"],"mimikyu-totem-busted":["disguise"],"mimikyu-totem-disguised":["disguise"],"minccino":["cute-charm","skill-link","technician"],"minior-blue":["shields-down"],"minior-blue-meteor":["shields-down"],"minior-green":["shields-down"],"minior-green-meteor":["shields-down"],"minior-indigo":["shields-down"],"minior-indigo-meteor":["shields-down"],"minior-orange":["shields-down"],"minior-orange-meteor":["shields-down"],"minior-red":["shields-down"],"minior-red-meteor":["shields-down"],"minior-violet":["shields-down"],"minior-violet-meteor":["shields-down"],"minior-yellow":["shields-down"],"minior-yellow-meteor":["shields-down"],"minun":["volt-absorb","minus"],"miraidon":["hadron-engine","hadron-engine"],"miraidon-aquatic-mode":["hadron-engine","hadron-engine"],"miraidon-drive-mode":["hadron-engine","hadron-engine"],"miraidon-glide-mode":["hadron-engine","hadron-engine"],"miraidon-low-power-mode":["hadron-engine","hadron-engine"],"misdreavus":["levitate"],"mismagius":["levitate"],"moltres":["pressure","flame-body"],"moltres-galar":["berserk"],"monferno":["blaze","iron-fist"],"morelull":["effect-spore","illuminate","rain-dish"],"morgrem":["frisk","pickpocket","prankster"],"morpeko-full-belly":["hunger-switch"],"morpeko-hangry":["hunger-switch"],"mothim":["swarm","tinted-lens"],"mr-mime":["soundproof","technician","filter"],"mr-mime-galar":["vital-spirit","ice-body","screen-cleaner"],"mr-rime":["tangled-feet","ice-body","screen-cleaner"],"mudbray":["own-tempo","inner-focus","stamina"],"mudkip":["damp","torrent"],"mudsdale":["own-tempo","inner-focus","stamina"],"muk":["stench","sticky-hold","poison-touch"],"muk-alola":["gluttony","poison-touch","power-of-alchemy"],"munchlax":["thick-fat","pickup","gluttony"],"munkidori":["frisk","toxic-chain"],"munna":["synchronize","forewarn","telepathy"],"murkrow":["insomnia","super-luck","prankster"],"musharna":["synchronize","forewarn","telepathy"],"nacli":["sturdy","clear-body","purifying-salt"],"naclstack":["sturdy","clear-body","purifying-salt"],"naganadel":["beast-boost"],"natu":["synchronize","early-bird","magic-bounce"],"necrozma":["prism-armor"],"necrozma-dawn":["prism-armor"],"necrozma-dusk":["prism-armor"],"necrozma-ultra":["neuroforce"],"nickit":["run-away","unburden","stakeout"],"nidoking":["poison-point","rivalry","sheer-force"],"nidoqueen":["poison-point","rivalry","sheer-force"],"nidoran-f":["poison-point","hustle","rivalry"],"nidoran-m":["poison-point","hustle","rivalry"],"nidorina":["poison-point","hustle","rivalry"],"nidorino":["poison-point","hustle","rivalry"],"nihilego":["beast-boost"],"nincada":["compound-eyes","run-away"],"ninetales":["flash-fire","drought"],"ninetales-alola":["snow-cloak","snow-warning"],"ninjask":["speed-boost","infiltrator"],"noctowl":["insomnia","keen-eye","tinted-lens"],"noibat":["frisk","telepathy","infiltrator"],"noivern":["frisk","telepathy","infiltrator"],"nosepass":["sturdy","magnet-pull","sand-force"],"numel":["oblivious","own-tempo","simple"],"nuzleaf":["chlorophyll","early-bird","pickpocket"],"nymble":["swarm","tinted-lens"],"obstagoon":["guts","reckless","defiant"],"octillery":["suction-cups","sniper","moody"],"oddish":["chlorophyll","run-away"],"ogerpon":["defiant"],"ogerpon-cornerstone-mask":["sturdy"],"ogerpon-hearthflame-mask":["mold-breaker"],"ogerpon-wellspring-mask":["water-absorb"],"oinkologne-female":["thick-fat","gluttony","aroma-veil"],"oinkologne-male":["thick-fat","gluttony","lingering-aroma"],"okidogi":["guard-dog","toxic-chain"],"omanyte":["swift-swim","shell-armor","weak-armor"],"omastar":["swift-swim","shell-armor","weak-armor"],"onix":["sturdy","rock-head","weak-armor"],"oranguru":["inner-focus","telepathy","symbiosis"],"orbeetle":["swarm","frisk","telepathy"],"orbeetle-gmax":["swarm","frisk","telepathy"],"oricorio-baile":["dancer"],"oricorio-pau":["dancer"],"oricorio-pom-pom":["dancer"],"oricorio-sensu":["dancer"],"orthworm":["sand-veil","earth-eater"],"oshawott":["torrent","shell-armor"],"overqwil":["intimidate","swift-swim","poison-point"],"pachirisu":["volt-absorb","run-away","pickup"],"palafin-hero":["zero-to-hero","zero-to-hero"],"palafin-zero":["zero-to-hero","zero-to-hero"],"palkia":["pressure","telepathy"],"palkia-origin":["pressure","telepathy"],"palossand":["sand-veil","water-compaction"],"palpitoad":["water-absorb","swift-swim","hydration"],"pancham":["iron-fist","mold-breaker","scrappy"],"pangoro":["iron-fist","mold-breaker","scrappy"],"panpour":["torrent","gluttony"],"pansage":["overgrow","gluttony"],"pansear":["blaze","gluttony"],"paras":["damp","effect-spore","dry-skin"],"parasect":["damp","effect-spore","dry-skin"],"passimian":["defiant","receiver"],"patrat":["run-away","keen-eye","analytic"],"pawmi":["static","natural-cure","iron-fist"],"pawmo":["volt-absorb","natural-cure","iron-fist"],"pawmot":["volt-absorb","natural-cure","iron-fist"],"pawniard":["inner-focus","pressure","defiant"],"pecharunt":["poison-puppeteer"],"pelipper":["drizzle","rain-dish","keen-eye"],"perrserker":["battle-armor","tough-claws","steely-spirit"],"persian":["limber","technician","unnerve"],"persian-alola":["technician","rattled","fur-coat"],"petilil":["own-tempo","chlorophyll","leaf-guard"],"phanpy":["sand-veil","pickup"],"phantump":["natural-cure","frisk","harvest"],"pheromosa":["beast-boost"],"phione":["hydration"],"pichu":["static","lightning-rod"],"pidgeot":["keen-eye","tangled-feet","big-pecks"],"pidgeot-mega":["no-guard"],"pidgeotto":["keen-eye","tangled-feet","big-pecks"],"pidgey":["keen-eye","tangled-feet","big-pecks"],"pidove":["rivalry","super-luck","big-pecks"],"pignite":["thick-fat","blaze"],"pikachu":["static","lightning-rod"],"pikachu-alola-cap":["static","lightning-rod"],"pikachu-belle":["static","lightning-rod"],"pikachu-cosplay":["static","lightning-rod"],"pikachu-gmax":["static","lightning-rod"],"pikachu-hoenn-cap":["static","lightning-rod"],"pikachu-kalos-cap":["static","lightning-rod"],"pikachu-libre":["static","lightning-rod"],"pikachu-original-cap":["static","lightning-rod"],"pikachu-partner-cap":["static","lightning-rod"],"pikachu-phd":["static","lightning-rod"],"pikachu-pop-star":["static","lightning-rod"],"pikachu-rock-star":["static","lightning-rod"],"pikachu-sinnoh-cap":["static","lightning-rod"],"pikachu-starter":["static","lightning-rod"],"pikachu-unova-cap":["static","lightning-rod"],"pikachu-world-cap":["static","lightning-rod"],"pikipek":["keen-eye","pickup","skill-link"],"piloswine":["oblivious","thick-fat","snow-cloak"],"pincurchin":["lightning-rod","electric-surge"],"pineco":["sturdy","overcoat"],"pinsir":["hyper-cutter","mold-breaker","moxie"],"pinsir-mega":["aerilate"],"piplup":["torrent","competitive"],"plusle":["lightning-rod","plus"],"poipole":["beast-boost"],"politoed":["drizzle","damp","water-absorb"],"poliwag":["damp","water-absorb","swift-swim"],"poliwhirl":["damp","water-absorb","swift-swim"],"poliwrath":["damp","water-absorb","swift-swim"],"poltchageist":["heatproof","hospitality"],"polteageist":["cursed-body","weak-armor"],"ponyta":["flash-fire","flame-body","run-away"],"ponyta-galar":["run-away","anticipation","pastel-veil"],"poochyena":["run-away","quick-feet","rattled"],"popplio":["torrent","liquid-voice"],"porygon":["trace","download","analytic"],"porygon-z":["download","adaptability","analytic"],"porygon2":["trace","download","analytic"],"primarina":["torrent","liquid-voice"],"primeape":["vital-spirit","anger-point","defiant"],"prinplup":["torrent","competitive"],"probopass":["sturdy","magnet-pull","sand-force"],"psyduck":["damp","cloud-nine","swift-swim"],"pumpkaboo-average":["insomnia","pickup","frisk"],"pumpkaboo-large":["insomnia","pickup","frisk"],"pumpkaboo-small":["insomnia","pickup","frisk"],"pumpkaboo-super":["insomnia","pickup","frisk"],"pupitar":["shed-skin"],"purrloin":["limber","unburden","prankster"],"purugly":["own-tempo","thick-fat","defiant"],"pyroar":["rivalry","unnerve","moxie"],"pyukumuku":["unaware","innards-out"],"quagsire":["damp","water-absorb","unaware"],"quaquaval":["torrent","moxie"],"quaxly":["torrent","moxie"],"quaxwell":["torrent","moxie"],"quilava":["flash-fire","blaze"],"quilladin":["overgrow","bulletproof"],"qwilfish":["intimidate","swift-swim","poison-point"],"qwilfish-hisui":["intimidate","swift-swim","poison-point"],"raboot":["blaze","libero"],"rabsca":["synchronize","telepathy"],"raging-bolt":["protosynthesis"],"raichu":["static","lightning-rod"],"raichu-alola":["surge-surfer"],"raikou":["inner-focus","pressure"],"ralts":["synchronize","trace","telepathy"],"rampardos":["mold-breaker","sheer-force"],"rapidash":["flash-fire","flame-body","run-away"],"rapidash-galar":["run-away","anticipation","pastel-veil"],"raticate":["run-away","hustle","guts"],"raticate-alola":["thick-fat","hustle","gluttony"],"raticate-totem-alola":["thick-fat","hustle","gluttony"],"rattata":["run-away","hustle","guts"],"rattata-alola":["thick-fat","hustle","gluttony"],"rayquaza":["air-lock"],"rayquaza-mega":["delta-stream"],"regice":["clear-body","ice-body"],"regidrago":["dragons-maw"],"regieleki":["transistor"],"regigigas":["slow-start"],"regirock":["sturdy","clear-body"],"registeel":["clear-body","light-metal"],"relicanth":["sturdy","swift-swim","rock-head"],"rellor":["compound-eyes","shed-skin"],"remoraid":["hustle","sniper","moody"],"reshiram":["turboblaze"],"reuniclus":["magic-guard","overcoat","regenerator"],"revavroom":["filter","overcoat"],"rhydon":["lightning-rod","rock-head","reckless"],"rhyhorn":["lightning-rod","rock-head","reckless"],"rhyperior":["lightning-rod","solid-rock","reckless"],"ribombee":["shield-dust","honey-gather","sweet-veil"],"ribombee-totem":["shield-dust","honey-gather","sweet-veil"],"rillaboom":["overgrow","grassy-surge"],"rillaboom-gmax":["overgrow","grassy-surge"],"riolu":["inner-focus","steadfast","prankster"],"roaring-moon":["protosynthesis","protosynthesis"],"rockruff":["keen-eye","vital-spirit","steadfast"],"rockruff-own-tempo":["own-tempo"],"roggenrola":["sturdy","weak-armor","sand-force"],"rolycoly":["flash-fire","heatproof","steam-engine"],"rookidee":["keen-eye","unnerve","big-pecks"],"roselia":["natural-cure","poison-point","leaf-guard"],"roserade":["natural-cure","poison-point","technician"],"rotom":["levitate"],"rotom-fan":["levitate"],"rotom-frost":["levitate"],"rotom-heat":["levitate"],"rotom-mow":["levitate"],"rotom-wash":["levitate"],"rowlet":["overgrow","long-reach"],"rufflet":["keen-eye","hustle","sheer-force"],"runerigus":["wandering-spirit"],"sableye":["keen-eye","stall","prankster"],"sableye-mega":["magic-bounce"],"salamence":["intimidate","moxie"],"salamence-mega":["aerilate"],"salandit":["oblivious","corrosion"],"salazzle":["oblivious","corrosion"],"salazzle-totem":["oblivious","corrosion"],"samurott":["torrent","shell-armor"],"samurott-hisui":["torrent","sharpness"],"sandaconda":["sand-veil","shed-skin","sand-spit"],"sandaconda-gmax":["sand-veil","shed-skin","sand-spit"],"sandile":["intimidate","anger-point","moxie"],"sandshrew":["sand-veil","sand-rush"],"sandshrew-alola":["snow-cloak","slush-rush"],"sandslash":["sand-veil","sand-rush"],"sandslash-alola":["snow-cloak","slush-rush"],"sandy-shocks":["protosynthesis","protosynthesis"],"sandygast":["sand-veil","water-compaction"],"sawk":["sturdy","inner-focus","mold-breaker"],"sawsbuck":["serene-grace","chlorophyll","sap-sipper"],"scatterbug":["compound-eyes","shield-dust","friend-guard"],"sceptile":["overgrow","unburden"],"sceptile-mega":["lightning-rod"],"scizor":["swarm","technician","light-metal"],"scizor-mega":["technician"],"scolipede":["speed-boost","poison-point","swarm"],"scorbunny":["blaze","libero"],"scovillain":["insomnia","chlorophyll","moody"],"scrafty":["intimidate","shed-skin","moxie"],"scraggy":["intimidate","shed-skin","moxie"],"scream-tail":["protosynthesis","protosynthesis"],"scyther":["swarm","steadfast","technician"],"seadra":["damp","poison-point","sniper"],"seaking":["lightning-rod","swift-swim","water-veil"],"sealeo":["oblivious","thick-fat","ice-body"],"seedot":["chlorophyll","early-bird","pickpocket"],"seel":["thick-fat","hydration","ice-body"],"seismitoad":["water-absorb","swift-swim","poison-touch"],"sentret":["run-away","keen-eye","frisk"],"serperior":["overgrow","contrary"],"servine":["overgrow","contrary"],"seviper":["shed-skin","infiltrator"],"sewaddle":["chlorophyll","swarm","overcoat"],"sharpedo":["speed-boost","rough-skin"],"sharpedo-mega":["strong-jaw"],"shaymin-land":["natural-cure"],"shaymin-sky":["serene-grace"],"shedinja":["wonder-guard"],"shelgon":["rock-head","overcoat"],"shellder":["shell-armor","skill-link","overcoat"],"shellos":["sticky-hold","storm-drain","sand-force"],"shelmet":["shell-armor","hydration","overcoat"],"shieldon":["sturdy","soundproof"],"shiftry":["chlorophyll","pickpocket","wind-rider"],"shiinotic":["effect-spore","illuminate","rain-dish"],"shinx":["intimidate","guts","rivalry"],"shroodle":["unburden","pickpocket","prankster"],"shroomish":["effect-spore","poison-heal","quick-feet"],"shuckle":["sturdy","gluttony","contrary"],"shuppet":["insomnia","frisk","cursed-body"],"sigilyph":["magic-guard","tinted-lens","wonder-skin"],"silcoon":["shed-skin"],"silicobra":["sand-veil","shed-skin","sand-spit"],"silvally":["rks-system"],"simipour":["torrent","gluttony"],"simisage":["overgrow","gluttony"],"simisear":["blaze","gluttony"],"sinistcha":["heatproof","hospitality"],"sinistea":["cursed-body","weak-armor"],"sirfetchd":["steadfast","scrappy"],"sizzlipede":["flash-fire","flame-body","white-smoke"],"skarmory":["sturdy","keen-eye","weak-armor"],"skeledirge":["blaze","unaware"],"skiddo":["sap-sipper","grass-pelt"],"skiploom":["chlorophyll","leaf-guard","infiltrator"],"skitty":["cute-charm","normalize","wonder-skin"],"skorupi":["battle-armor","keen-eye","sniper"],"skrelp":["poison-point","adaptability","poison-touch"],"skuntank":["stench","keen-eye","aftermath"],"skwovet":["gluttony","cheek-pouch"],"slaking":["truant"],"slakoth":["truant"],"sliggoo":["hydration","sap-sipper","gooey"],"sliggoo-hisui":["shell-armor","sap-sipper","gooey"],"slither-wing":["protosynthesis","protosynthesis"],"slowbro":["oblivious","own-tempo","regenerator"],"slowbro-galar":["own-tempo","regenerator","quick-draw"],"slowbro-mega":["shell-armor"],"slowking":["oblivious","own-tempo","regenerator"],"slowking-galar":["own-tempo","regenerator","curious-medicine"],"slowpoke":["oblivious","own-tempo","regenerator"],"slowpoke-galar":["own-tempo","gluttony","regenerator"],"slugma":["magma-armor","flame-body","weak-armor"],"slurpuff":["unburden","sweet-veil"],"smeargle":["own-tempo","technician","moody"],"smoliv":["early-bird","harvest"],"smoochum":["oblivious","hydration","forewarn"],"sneasel":["inner-focus","keen-eye","pickpocket"],"sneasel-hisui":["inner-focus","keen-eye","pickpocket"],"sneasler":["pressure","unburden","poison-touch"],"snivy":["overgrow","contrary"],"snom":["shield-dust","ice-scales"],"snorlax":["immunity","thick-fat","gluttony"],"snorlax-gmax":["immunity","thick-fat","gluttony"],"snorunt":["inner-focus","ice-body","moody"],"snover":["soundproof","snow-warning"],"snubbull":["intimidate","run-away","rattled"],"sobble":["torrent","sniper"],"solgaleo":["full-metal-body"],"solosis":["magic-guard","overcoat","regenerator"],"solrock":["levitate"],"spearow":["keen-eye","sniper"],"spectrier":["grim-neigh"],"spewpa":["shed-skin","friend-guard"],"spheal":["oblivious","thick-fat","ice-body"],"spidops":["insomnia","stakeout"],"spinarak":["insomnia","swarm","sniper"],"spinda":["own-tempo","tangled-feet","contrary"],"spiritomb":["pressure","infiltrator"],"spoink":["own-tempo","thick-fat","gluttony"],"sprigatito":["overgrow","protean"],"spritzee":["healer","aroma-veil"],"squawkabilly-blue-plumage":["intimidate","hustle","guts"],"squawkabilly-green-plumage":["intimidate","hustle","guts"],"squawkabilly-white-plumage":["intimidate","hustle","sheer-force"],"squawkabilly-yellow-plumage":["intimidate","hustle","sheer-force"],"squirtle":["rain-dish","torrent"],"stakataka":["beast-boost"],"stantler":["intimidate","frisk","sap-sipper"],"staraptor":["intimidate","reckless"],"staravia":["intimidate","reckless"],"starly":["keen-eye","reckless"],"starmie":["natural-cure","illuminate","analytic"],"staryu":["natural-cure","illuminate","analytic"],"steelix":["sturdy","rock-head","sheer-force"],"steelix-mega":["sand-force"],"steenee":["oblivious","leaf-guard","sweet-veil"],"stonjourner":["power-spot"],"stoutland":["intimidate","scrappy","sand-rush"],"stufful":["cute-charm","klutz","fluffy"],"stunfisk":["limber","sand-veil","static"],"stunfisk-galar":["mimicry"],"stunky":["stench","keen-eye","aftermath"],"sudowoodo":["sturdy","rock-head","rattled"],"suicune":["inner-focus","pressure"],"sunflora":["chlorophyll","early-bird","solar-power"],"sunkern":["chlorophyll","early-bird","solar-power"],"surskit":["swift-swim","rain-dish"],"swablu":["cloud-nine","natural-cure"],"swadloon":["chlorophyll","leaf-guard","overcoat"],"swalot":["sticky-hold","liquid-ooze","gluttony"],"swampert":["damp","torrent"],"swampert-mega":["swift-swim"],"swanna":["keen-eye","hydration","big-pecks"],"swellow":["guts","scrappy"],"swinub":["oblivious","thick-fat","snow-cloak"],"swirlix":["unburden","sweet-veil"],"swoobat":["simple","klutz","unaware"],"sylveon":["cute-charm","pixilate"],"tadbulb":["damp","static","own-tempo"],"taillow":["guts","scrappy"],"talonflame":["flame-body","gale-wings"],"tandemaus":["own-tempo","run-away","pickup"],"tangela":["chlorophyll","leaf-guard","regenerator"],"tangrowth":["chlorophyll","leaf-guard","regenerator"],"tapu-bulu":["telepathy","grassy-surge"],"tapu-fini":["telepathy","misty-surge"],"tapu-koko":["telepathy","electric-surge"],"tapu-lele":["telepathy","psychic-surge"],"tarountula":["insomnia","stakeout"],"tatsugiri-curly":["storm-drain","commander"],"tatsugiri-droopy":["storm-drain","commander"],"tatsugiri-stretchy":["storm-drain","commander"],"tauros":["intimidate","anger-point","sheer-force"],"tauros-paldea-aqua-breed":["intimidate","anger-point","cud-chew"],"tauros-paldea-blaze-breed":["intimidate","anger-point","cud-chew"],"tauros-paldea-combat-breed":["intimidate","anger-point","cud-chew"],"teddiursa":["pickup","quick-feet","honey-gather"],"tentacool":["clear-body","rain-dish","liquid-ooze"],"tentacruel":["clear-body","rain-dish","liquid-ooze"],"tepig":["thick-fat","blaze"],"terapagos":["tera-shift"],"terapagos-stellar":["teraform-zero"],"terapagos-terastal":["tera-shell"],"terrakion":["justified"],"thievul":["run-away","unburden","stakeout"],"throh":["inner-focus","guts","mold-breaker"],"thundurus-incarnate":["defiant","prankster"],"thundurus-therian":["volt-absorb"],"thwackey":["overgrow","grassy-surge"],"timburr":["guts","iron-fist","sheer-force"],"ting-lu":["vessel-of-ruin","vessel-of-ruin"],"tinkatink":["own-tempo","mold-breaker","pickpocket"],"tinkaton":["own-tempo","mold-breaker","pickpocket"],"tinkatuff":["own-tempo","mold-breaker","pickpocket"],"tirtouga":["sturdy","swift-swim","solid-rock"],"toedscool":["mycelium-might","mycelium-might"],"toedscruel":["mycelium-might","mycelium-might"],"togedemaru":["sturdy","lightning-rod","iron-barbs"],"togedemaru-totem":["sturdy","lightning-rod","iron-barbs"],"togekiss":["serene-grace","hustle","super-luck"],"togepi":["serene-grace","hustle","super-luck"],"togetic":["serene-grace","hustle","super-luck"],"torchic":["speed-boost","blaze"],"torkoal":["drought","white-smoke","shell-armor"],"tornadus-incarnate":["defiant","prankster"],"tornadus-therian":["regenerator"],"torracat":["intimidate","blaze"],"torterra":["overgrow","shell-armor"],"totodile":["torrent","sheer-force"],"toucannon":["keen-eye","skill-link","sheer-force"],"toxapex":["limber","regenerator","merciless"],"toxel":["static","klutz","rattled"],"toxicroak":["dry-skin","anticipation","poison-touch"],"toxtricity-amped":["plus","technician","punk-rock"],"toxtricity-amped-gmax":["plus","technician","punk-rock"],"toxtricity-low-key":["minus","technician","punk-rock"],"toxtricity-low-key-gmax":["minus","technician","punk-rock"],"tranquill":["rivalry","super-luck","big-pecks"],"trapinch":["hyper-cutter","arena-trap","sheer-force"],"treecko":["overgrow","unburden"],"trevenant":["natural-cure","frisk","harvest"],"tropius":["chlorophyll","solar-power","harvest"],"trubbish":["stench","sticky-hold","aftermath"],"trumbeak":["keen-eye","pickup","skill-link"],"tsareena":["leaf-guard","sweet-veil","queenly-majesty"],"turtonator":["shell-armor"],"turtwig":["overgrow","shell-armor"],"tympole":["water-absorb","swift-swim","hydration"],"tynamo":["levitate"],"type-null":["battle-armor"],"typhlosion":["flash-fire","blaze"],"typhlosion-hisui":["blaze","frisk"],"tyranitar":["sand-stream","unnerve"],"tyranitar-mega":["sand-stream"],"tyrantrum":["rock-head","strong-jaw"],"tyrogue":["guts","vital-spirit","steadfast"],"tyrunt":["sturdy","strong-jaw"],"umbreon":["synchronize","inner-focus"],"unfezant":["rivalry","super-luck","big-pecks"],"unown":["levitate"],"ursaluna":["guts","unnerve","bulletproof"],"ursaluna-bloodmoon":["minds-eye"],"ursaring":["guts","quick-feet","unnerve"],"urshifu-rapid-strike":["unseen-fist"],"urshifu-rapid-strike-gmax":["unseen-fist"],"urshifu-single-strike":["unseen-fist"],"urshifu-single-strike-gmax":["unseen-fist"],"uxie":["levitate"],"vanillish":["snow-cloak","ice-body","weak-armor"],"vanillite":["snow-cloak","ice-body","weak-armor"],"vanilluxe":["ice-body","snow-warning","weak-armor"],"vaporeon":["water-absorb","hydration"],"varoom":["slow-start","overcoat"],"veluza":["mold-breaker","sharpness"],"venipede":["speed-boost","poison-point","swarm"],"venomoth":["shield-dust","tinted-lens","wonder-skin"],"venonat":["compound-eyes","run-away","tinted-lens"],"venusaur":["chlorophyll","overgrow"],"venusaur-gmax":["chlorophyll","overgrow"],"venusaur-mega":["thick-fat"],"vespiquen":["pressure","unnerve"],"vibrava":["levitate"],"victini":["victory-star"],"victreebel":["chlorophyll","gluttony"],"vigoroth":["vital-spirit"],"vikavolt":["levitate"],"vikavolt-totem":["levitate"],"vileplume":["effect-spore","chlorophyll"],"virizion":["justified"],"vivillon":["compound-eyes","shield-dust","friend-guard"],"volbeat":["illuminate","swarm","prankster"],"volcanion":["water-absorb"],"volcarona":["flame-body","swarm"],"voltorb":["static","soundproof","aftermath"],"voltorb-hisui":["static","soundproof","aftermath"],"vullaby":["weak-armor","overcoat","big-pecks"],"vulpix":["flash-fire","drought"],"vulpix-alola":["snow-cloak","snow-warning"],"wailmer":["oblivious","water-veil","pressure"],"wailord":["oblivious","water-veil","pressure"],"walking-wake":["protosynthesis","protosynthesis"],"walrein":["oblivious","thick-fat","ice-body"],"wartortle":["rain-dish","torrent"],"watchog":["illuminate","keen-eye","analytic"],"wattrel":["volt-absorb","competitive","wind-power"],"weavile":["pressure","pickpocket"],"weedle":["shield-dust","run-away"],"weepinbell":["chlorophyll","gluttony"],"weezing":["stench","levitate","neutralizing-gas"],"weezing-galar":["levitate","misty-surge","neutralizing-gas"],"whimsicott":["chlorophyll","infiltrator","prankster"],"whirlipede":["speed-boost","poison-point","swarm"],"whiscash":["oblivious","hydration","anticipation"],"whismur":["soundproof","rattled"],"wigglytuff":["cute-charm","frisk","competitive"],"wiglett":["sand-veil","rattled","gooey"],"wimpod":["wimp-out"],"wingull":["rain-dish","keen-eye","hydration"],"wishiwashi-school":["schooling"],"wishiwashi-solo":["schooling"],"wo-chien":["tablets-of-ruin","tablets-of-ruin"],"wobbuffet":["shadow-tag","telepathy"],"woobat":["simple","klutz","unaware"],"wooloo":["run-away","bulletproof","fluffy"],"wooper":["damp","water-absorb","unaware"],"wooper-paldea":["water-absorb","poison-point","unaware"],"wormadam-plant":["anticipation","overcoat"],"wormadam-sandy":["anticipation","overcoat"],"wormadam-trash":["anticipation","overcoat"],"wugtrio":["sand-veil","rattled","gooey"],"wurmple":["shield-dust","run-away"],"wynaut":["shadow-tag","telepathy"],"wyrdeer":["intimidate","frisk","sap-sipper"],"xatu":["synchronize","early-bird","magic-bounce"],"xerneas":["fairy-aura"],"xurkitree":["beast-boost"],"yamask":["mummy"],"yamask-galar":["wandering-spirit"],"yamper":["rattled","ball-fetch"],"yanma":["speed-boost","compound-eyes","frisk"],"yanmega":["speed-boost","tinted-lens","frisk"],"yungoos":["adaptability","strong-jaw","stakeout"],"yveltal":["dark-aura"],"zacian":["intrepid-sword"],"zacian-crowned":["intrepid-sword"],"zamazenta":["dauntless-shield"],"zamazenta-crowned":["dauntless-shield"],"zangoose":["immunity","toxic-boost"],"zapdos":["static","pressure"],"zapdos-galar":["defiant"],"zarude":["leaf-guard"],"zarude-dada":["leaf-guard"],"zebstrika":["lightning-rod","motor-drive","sap-sipper"],"zekrom":["teravolt"],"zeraora":["volt-absorb"],"zigzagoon":["pickup","gluttony","quick-feet"],"zigzagoon-galar":["pickup","gluttony","quick-feet"],"zoroark":["illusion"],"zoroark-hisui":["illusion"],"zorua":["illusion"],"zorua-hisui":["illusion"],"zubat":["inner-focus","infiltrator"],"zweilous":["hustle"],"zygarde-10":["aura-break"],"zygarde-10-power-construct":["power-construct"],"zygarde-50":["aura-break"],"zygarde-50-power-construct":["power-construct"],"zygarde-complete":["power-construct"]}